argovisHelpers/__init__.py
argovisHelpers/gridtools.py
argovisHelpers/helpers.py
argovisHelpers-0.0.33.dist-info/LICENSE
argovisHelpers-0.0.33.dist-info/METADATA
argovisHelpers-0.0.33.dist-info/WHEEL
argovisHelpers-0.0.33.dist-info/top_level.txt
argovisHelpers-0.0.33.dist-info/RECORD
