Metadata-Version: 2.2
Name: argovisHelpers
Version: 0.0.33
Summary: Helper functions to consume and parse information from University of Colorado's Argovis API.
Author: Katie Mills
License: Copyright (c) 2023 Argovis
Project-URL: Homepage, https://argovis.colorado.edu
Classifier: License :: OSI Approved :: MIT License
Classifier: Programming Language :: Python
Classifier: Programming Language :: Python :: 3
Requires-Python: >=3.9
License-File: LICENSE
Requires-Dist: requests
Requires-Dist: area
Requires-Dist: shapely==1.8.0
Requires-Dist: geopandas
